setup.py
tic_tac_toe_rv_yw/__init__.py
tic_tac_toe_rv_yw/tic_tac_toe.py
tic_tac_toe_rv_yw.egg-info/PKG-INFO
tic_tac_toe_rv_yw.egg-info/SOURCES.txt
tic_tac_toe_rv_yw.egg-info/dependency_links.txt
tic_tac_toe_rv_yw.egg-info/not-zip-safe
tic_tac_toe_rv_yw.egg-info/top_level.txt