Metadata-Version: 1.0
Name: tic-tac-toe-rv-yw
Version: 0.1
Summary: A fun take on the traditional game.
Home-page: UNKNOWN
Author: Rahul Vaswani, Yifei Wang
Author-email: firstname_first3lettersoflast@gmail.com
License: UNKNOWN
Platform: UNKNOWN
